mteval/__init__.py
mteval/_modidx.py
mteval/awsmt.py
mteval/bleu.py
mteval/comet.py
mteval/dataset.py
mteval/deeplmt.py
mteval/googlemt.py
mteval/microsoftmt.py
mteval/modernmt.py
mteval/ter.py
mteval/util.py
mteval-0.0.2.dist-info/LICENSE
mteval-0.0.2.dist-info/METADATA
mteval-0.0.2.dist-info/WHEEL
mteval-0.0.2.dist-info/entry_points.txt
mteval-0.0.2.dist-info/top_level.txt
mteval-0.0.2.dist-info/RECORD
