Metadata-Version: 2.1
Name: mteval
Version: 0.0.2
Summary: Library to automate machine translation evaluation
Home-page: https://github.com/achimr/mteval
Author: Achim Ruopp
Author-email: achimru@gmail.com
License: Apache Software License 2.0
Keywords: nbdev jupyter notebook python
Platform: UNKNOWN
Classifier: Development Status :: 4 - Beta
Classifier: Intended Audience :: Developers
Classifier: Natural Language :: English
Classifier: Programming Language :: Python :: 3.7
Classifier: Programming Language :: Python :: 3.8
Classifier: Programming Language :: Python :: 3.9
Classifier: Programming Language :: Python :: 3.10
Classifier: License :: OSI Approved :: Apache Software License
Requires-Python: >=3.7
Requires-Dist: boto3
Requires-Dist: deepl
Requires-Dist: google-cloud-translate
Requires-Dist: langcodes
Requires-Dist: modernmt
Requires-Dist: python-dotenv[cli]
Requires-Dist: requests
Requires-Dist: sacrebleu[ja,ko]
Requires-Dist: unbabel-comet
Provides-Extra: dev
